iterr/__init__.py
iterr-0.1.0.dist-info/LICENSE
iterr-0.1.0.dist-info/METADATA
iterr-0.1.0.dist-info/WHEEL
iterr-0.1.0.dist-info/top_level.txt
iterr-0.1.0.dist-info/RECORD
