Metadata-Version: 2.1
Name: iterr
Version: 0.1.0
Summary: type-checked, lazy, rust-styled iterator
Home-page: https://github.com/YilunAllenChen/iter
Author: Allen Chen
Author-email: allenchenyilun1999@gmail.com
Classifier: Programming Language :: Python :: 3
Classifier: License :: OSI Approved :: MIT License
Classifier: Operating System :: OS Independent
Requires-Python: >=3.6
License-File: LICENSE
